{
    "ID" : "hardpointdatadef_wasp",
    "HardpointData" : [
        {
            "location" : "leftleg",
            "weapons" : [
                [
                    "chrprfweap_wasp_leftleg_flamer_eh1",
                    "chrprfweap_wasp_leftleg_laser_eh1",
                    "chrprfweap_wasp_leftleg_missile2_mh1"
                ]
            ],
            "blanks" : [
                
            ],
            "mountingPoints" : [
                
            ]
        },
        {
            "location" : "lefttorso",
            "weapons" : [
                [
                    "chrprfweap_wasp_lefttorso_flamer_eh1",
                    "chrprfweap_wasp_lefttorso_laser_eh1",
                    "chrprfweap_wasp_lefttorso_mg_bh1",
                    "chrprfweap_wasp_lefttorso_missile10_mh1"
                ],
                [
                    "chrprfweap_wasp_lefttorso_flamer_eh2",
                    "chrprfweap_wasp_lefttorso_laser_eh2"
                ]
            ],
            "blanks" : [
                
            ],
            "mountingPoints" : [
                
            ]
        },
        {
            "location" : "rightarm",
            "weapons" : [
                [
                    "chrprfweap_wasp_rightarm_flamer_eh1",
                    "chrprfweap_wasp_rightarm_laser_eh1",
                    "chrprfweap_wasp_rightarm_mg_bh1",
                    "chrprfweap_wasp_rightarm_missile4_mh1",
                    "chrprfweap_wasp_rightarm_ppc_eh1"
                ],
                [
                    "chrprfweap_wasp_rightarm_flamer_eh2",
                    "chrprfweap_wasp_rightarm_laser_eh2",
                    "chrprfweap_wasp_rightarm_mg_bh2"
                ]
            ],
            "blanks" : [
                
            ],
            "mountingPoints" : [
                
            ]
        },
        {
            "location" : "righttorso",
            "weapons" : [
                [
                    "chrprfweap_wasp_righttorso_flamer_eh1",
                    "chrprfweap_wasp_righttorso_laser_eh1",
                    "chrprfweap_wasp_righttorso_mg_bh1",
                    "chrprfweap_wasp_righttorso_missile10_mh1"
                ],
                [
                    "chrprfweap_wasp_righttorso_flamer_eh2",
                    "chrprfweap_wasp_righttorso_laser_eh2"
                ]
            ],
            "blanks" : [
                
            ],
            "mountingPoints" : [
                
            ]
        }
    ]
}