{
    "ID" : "hardpointdatadef_vossieostscout",
    "HardpointData" : [
        {
            "location" : "leftarm",
            "weapons" : [
			[
			"chrprfweap_vossieostscout_leftarm_laser_eh1"
			]
			],
            "blanks" : [

            ],
            "mountingPoints" : [
                
            ]
        },
        {
            "location" : "lefttorso",
            "weapons" : [
			[
			"chrprfweap_vossieostscout_lefttorso_laser_eh1"
			]
			],
            "blanks" : [
			
            ],
            "mountingPoints" : [
                
            ]
        },
        {
            "location" : "rightarm",
            "weapons" : [
			[
			"chrprfweap_vossieostscout_rightarm_laser_eh1"
			]
			],
            "blanks" : [
                
            ],
            "mountingPoints" : [
                
            ]
        },
        {
            "location" : "righttorso",
            "weapons" : [
			[
			"chrprfweap_vossieostscout_righttorso_laser_eh1"
			]
			],
            "blanks" : [
			
            ],
            "mountingPoints" : [
                
            ]
        },
		{
            "location" : "centertorso",
            "weapons" : [],
            "blanks" : [
                
            ],
            "mountingPoints" : [
                
            ]
        }
    ]
	
}